README.md
setup.py
rocket_pack/setup.py
rocket_pack.egg-info/PKG-INFO
rocket_pack.egg-info/SOURCES.txt
rocket_pack.egg-info/dependency_links.txt
rocket_pack.egg-info/top_level.txt