Metadata-Version: 2.1
Name: rocket-pack
Version: 0.1
Summary: A package to simulate rockets and shuttles
Home-page: https://pypi.org/user/Islem_ord/
Author: islem
Author-email: ic.ourred@esi-sba.dz
License: LICENSE.txt
